{
  "people": {
    "Bobby Ludlam": {
      "name": "Bobby Ludlam",
      "url": "https://www.bobbyludlam.com",
      "same_as": [
        "https://www.bobbyludlam.com",
        "https://www.instagram.com/bobbyludlam/"
      ],
      "roles": ["Comedian", "Security", "Self"],
      "job_title": "Self",
      "credit_note": "One of the three best friends at the heart of the documentary, a comedian chasing stage time and a bigger creative dream."
    },
    "Corey Pellizzi": {
      "name": "Corey Pellizzi",
      "url": "https://instagram.com/owlmovement",
      "same_as": ["https://instagram.com/owlmovement"],
      "roles": ["Comedian", "Director", "Producer", "Security", "Self"],
      "job_title": "Director, Producer",
      "credit_note": "Directing, filming, and drawn to places of his childhood, creativity and freedom."
    },
    "Georg Sinn": {
      "name": "Georg Sinn",
      "url": "https://zwitschi.net",
      "same_as": [
        "https://zwitschi.net",
        "https://allucanget.biz",
        "https://www.instagram.com/allucanget"
      ],
      "roles": [
        "Manager",
        "Driver",
        "Traveler",
        "Security",
        "Self",
        "Producer"
      ],
      "job_title": "Producer",
      "credit_note": "From far away, driving across America and keeping the crew rolling toward the next place to film, perform, and connect with the comedy world. Infrastructure, logistics, IT, development, finance."
    },
    "Open Mic Odyssey Team": {
      "name": "Open Mic Odyssey Team",
      "url": "https://openmicodyssey.com",
      "same_as": ["https://openmicodyssey.com"],
      "roles": ["Director", "Producer"],
      "job_title": "Director",
      "credit_note": "Shapes the documentary point of view and guides the on-the-road narrative structure. Coordinates production, release planning, and how the film reaches audiences."
    }
  },
  "contributors": {
    "directors": [
      {
        "name": "Corey Pellizzi",
        "job_title": "Director",
        "url": "https://coreypellizzi.com",
        "same_as": ["https://coreypellizzi.com"],
        "credit_note": "Shapes the documentary point of view and guides the on-the-road narrative structure."
      }
    ],
    "producers": [
      {
        "name": "Corey Pellizzi",
        "job_title": "Producer",
        "url": "https://coreypellizzi.com",
        "same_as": ["https://coreypellizzi.com"],
        "credit_note": "Coordinates production, release planning, and how the film reaches audiences."
      },
      {
        "name": "Georg Sinn",
        "job_title": "Producer",
        "url": "https://allucanget.biz",
        "same_as": [
          "https://zwitschi.net",
          "https://allucanget.biz",
          "https://www.instagram.com/allucanget"
        ],
        "credit_note": "Infrastructure, logistics, IT, development, finance."
      }
    ],
    "actors": [
      {
        "name": "Bobby Ludlam",
        "job_title": "Self",
        "url": "https://www.bobbyludlam.com",
        "same_as": [
          "https://www.bobbyludlam.com",
          "https://www.instagram.com/bobbyludlam/"
        ],
        "credit_note": "One of the three best friends at the heart of the documentary, a comedian chasing stage time and a bigger creative dream."
      },
      {
        "name": "Corey Pellizzi",
        "job_title": "Self",
        "url": "https://instagram.com/owlmovement",
        "same_as": ["https://instagram.com/owlmovement"],
        "credit_note": "Directing, filming, and drawn to places of his childhood, creativity and freedom."
      },
      {
        "name": "Georg Sinn",
        "job_title": "Self",
        "url": "https://zwitschi.net",
        "same_as": [
          "https://zwitschi.net",
          "https://allucanget.biz",
          "https://www.instagram.com/allucanget"
        ],
        "credit_note": "From far away, driving across America and keeping the crew rolling toward the next place to film, perform, and connect with the comedy world."
      }
    ]
  },
  "credits_people": [
    {
      "name": "Bobby Ludlam",
      "roles": ["Comedian", "Security"],
      "primary_url": "https://www.bobbyludlam.com",
      "same_as": [
        "https://www.bobbyludlam.com",
        "https://www.instagram.com/bobbyludlam/"
      ]
    },
    {
      "name": "Corey Pellizzi",
      "roles": ["Comedian", "Director", "Producer", "Security"],
      "primary_url": "https://instagram.com/owlmovement",
      "same_as": ["https://instagram.com/owlmovement"]
    },
    {
      "name": "Georg Sinn",
      "roles": ["Manager", "Driver", "Traveler", "Security"],
      "primary_url": "https://zwitschi.net",
      "same_as": [
        "https://zwitschi.net",
        "https://allucanget.biz",
        "https://www.instagram.com/allucanget"
      ]
    }
  ]
}
